centrex_hamiltonian_streamlit/__init__.py
centrex_hamiltonian_streamlit/cli.py
centrex_hamiltonian_streamlit/data/B_state_ham.pkl
centrex_hamiltonian_streamlit/data/X_state_ham.pkl
centrex_hamiltonian_streamlit/dataframe.py
centrex_hamiltonian_streamlit/generate_precomputed_B_hamiltonian.py
centrex_hamiltonian_streamlit/generate_precomputed_X_hamiltonian.py
centrex_hamiltonian_streamlit/hamiltonian.py
centrex_hamiltonian_streamlit/main.py
centrex_hamiltonian_streamlit/pages/__init__.py
centrex_hamiltonian_streamlit/pages/level_scheme.py
centrex_hamiltonian_streamlit/pages/transition_levels.py
centrex_hamiltonian_streamlit/plot.py
centrex_hamiltonian_streamlit-0.1.0.dist-info/entry_points.txt
centrex_hamiltonian_streamlit-0.1.0.dist-info/LICENSE
centrex_hamiltonian_streamlit-0.1.0.dist-info/METADATA
centrex_hamiltonian_streamlit-0.1.0.dist-info/WHEEL
centrex_hamiltonian_streamlit-0.1.0.dist-info/RECORD
