Metadata-Version: 2.1
Name: centrex-hamiltonian-streamlit
Version: 0.1.0
Summary: Streamlit app for the TlF hamiltonian
License: MIT
Author: ograsdijk
Author-email: o.grasdijk@gmail.com
Requires-Python: >=3.11,<4.0
Classifier: License :: OSI Approved :: MIT License
Classifier: Programming Language :: Python :: 3
Classifier: Programming Language :: Python :: 3.11
Classifier: Programming Language :: Python :: 3.12
Requires-Dist: centrex-tlf (>=0.1.3,<0.2.0)
Requires-Dist: numpy (>=1.26.4,<2.0.0)
Requires-Dist: pandas (>=2.2.2,<3.0.0)
Requires-Dist: plotly (>=5.22.0,<6.0.0)
Requires-Dist: streamlit (>=1.35.0,<2.0.0)
Requires-Dist: streamlit-navigation-bar (>=3.3.0,<4.0.0)
